{
	"info": {
		"_postman_id": "86a835dd-c03a-4b4b-87b3-1de00126d141",
		"name": "blog_api",
		"schema": "https://schema.getpostman.com/json/collection/v2.1.0/collection.json",
		"_exporter_id": "48356072",
		"_collection_link": "https://dhartin-webosmotic-7658298.postman.co/workspace/Dharti-Navadiya's-Workspace~e07324b4-053d-4c5e-82d4-26fc252cc3e0/collection/48356072-86a835dd-c03a-4b4b-87b3-1de00126d141?action=share&source=collection_link&creator=48356072"
	},
	"item": [
		{
			"name": "New Request",
			"request": {
				"method": "POST",
				"header": [],
				"body": {
					"mode": "raw",
					"raw": "{\r\n  \"session_id\": \"th-1\",\r\n  \"topic\": \"AI impact in tech 2025\",\r\n  \"tone\": \"Professional\",\r\n  \"length\": 200\r\n}",
					"options": {
						"raw": {
							"language": "json"
						}
					}
				},
				"url": {
					"raw": "http://localhost:5000/generate\n",
					"protocol": "http",
					"host": [
						"localhost"
					],
					"port": "5000",
					"path": [
						"generate\n"
					]
				}
			},
			"response": []
		},
		{
			"name": "New Request",
			"request": {
				"method": "POST",
				"header": [],
				"body": {
					"mode": "raw",
					"raw": "{\r\n  \"session_id\": \"th-1\",\r\n  \"user_feedback\": \"remove Conclusion\"\r\n}\r\n",
					"options": {
						"raw": {
							"language": "json"
						}
					}
				},
				"url": {
					"raw": "http://localhost:5000/user_input\n",
					"protocol": "http",
					"host": [
						"localhost"
					],
					"port": "5000",
					"path": [
						"user_input\n"
					]
				}
			},
			"response": []
		}
	]
}